quant_analytics/__init__.py
quant_analytics/result.py
quant_analytics/utils.py
quant_analytics/analysis/__init__.py
quant_analytics/analysis/plots.py
quant_analytics/backtest/__init__.py
quant_analytics/backtest/backtester.py
quant_analytics/backtest/base_strategy.py
quant_analytics/backtest/metrics.py
quant_analytics/data/__init__.py
quant_analytics/data/generator.py
quant_analytics/data/handler.py
quant_analytics/report/__init__.py
quant_analytics/report/report.py
quant_analytics/statistics/__init__.py
quant_analytics/statistics/results.py
quant_analytics/statistics/statistics.py
quant_analytics-1.0.7.dist-info/LICENSE
quant_analytics-1.0.7.dist-info/METADATA
quant_analytics-1.0.7.dist-info/WHEEL
quant_analytics-1.0.7.dist-info/top_level.txt
quant_analytics-1.0.7.dist-info/RECORD
